offal/__init__.py
offal/__main__.py
offal/main.py
offal/py.typed
offal/py.typed
offal-0.1.1.dist-info/METADATA
offal-0.1.1.dist-info/WHEEL
offal-0.1.1.dist-info/entry_points.txt
offal-0.1.1.dist-info/licenses/LICENSE
offal-0.1.1.dist-info/RECORD
