Metadata-Version: 2.3
Name: offal
Version: 0.1.1
Summary: Add your description here
Author-email: Matthew White <matthew.r.j.white@gmail.com>
License-File: LICENSE
Requires-Python: >=3.8
Requires-Dist: gitpython>=3.1.43
Requires-Dist: typer>=0.12.4
